MANIFEST.in
README.md
setup.py
Pommie/LICENSE.txt
Pommie/__init__.py
Pommie/compute.py
Pommie/opengl.py
Pommie/typedefs.py
Pommie/util.py
Pommie.egg-info/PKG-INFO
Pommie.egg-info/SOURCES.txt
Pommie.egg-info/dependency_links.txt
Pommie.egg-info/requires.txt
Pommie.egg-info/top_level.txt
Pommie/shaders/__init__.py
Pommie/shaders/center_of_mass.glsl
Pommie/shaders/empty_buffer.glsl
Pommie/shaders/resample_3d_texture.glsl
Pommie/shaders/separable_filter.glsl
Pommie/shaders/similarity_functions.glsl
Pommie/shaders/template_match.glsl
Pommie/shaders/template_match_2d.glsl
Pommie/shaders/write_max_score_to_volume.glsl